gitlab_backup/__init__.py
gitlab_backup-0.5.1.data/scripts/gitlab-backup
gitlab_backup-0.5.1.dist-info/LICENSE.txt
gitlab_backup-0.5.1.dist-info/METADATA
gitlab_backup-0.5.1.dist-info/WHEEL
gitlab_backup-0.5.1.dist-info/top_level.txt
gitlab_backup-0.5.1.dist-info/zip-safe
gitlab_backup-0.5.1.dist-info/RECORD
