Metadata-Version: 2.1
Name: gitlab-backup
Version: 0.5.1
Summary: backup a gitlab user or organization
Home-page: http://github.com/josegonzalez/python-gitlab-backup
Author: Jose Diaz-Gonzalez
Author-email: gitlab-backup@josediazgonzalez.com
License: MIT
Platform: UNKNOWN
Classifier: Development Status :: 5 - Production/Stable
Classifier: Topic :: System :: Archiving :: Backup
Classifier: License :: OSI Approved :: MIT License
Classifier: Programming Language :: Python :: 3.5
Classifier: Programming Language :: Python :: 3.6
Classifier: Programming Language :: Python :: 3.7
Classifier: Programming Language :: Python :: 3.8
Requires-Dist: python-gitlab
